bageltushare/__init__.py
bageltushare/database.py
bageltushare/example.py
bageltushare/query.py
bageltushare/save_and_log.py
bageltushare/tushare_api.py
bageltushare/tushare_downloader.py
bageltushare-0.0.4.dist-info/LICENSE
bageltushare-0.0.4.dist-info/METADATA
bageltushare-0.0.4.dist-info/WHEEL
bageltushare-0.0.4.dist-info/top_level.txt
bageltushare-0.0.4.dist-info/RECORD
