Metadata-Version: 2.1
Name: bageltushare
Version: 0.0.4
Summary: A package for download China A market stock data using tushare api, and automatically store to a local database
Author-email: Yanzhong Huang <eric.yanzhong.huang@gmail.com>
Project-URL: Homepage, https://github.com/bagelquant/bageltushare
Project-URL: Issues, https://github.com/bagelquant/bageltushare/issues
Classifier: Programming Language :: Python :: 3
Classifier: License :: OSI Approved :: MIT License
Classifier: Operating System :: OS Independent
Requires-Python: >=3.10
License-File: LICENSE
Requires-Dist: pandas>=2.2.0
Requires-Dist: tushare>=1.4.0
Requires-Dist: pymysql>=1.1.1
Requires-Dist: sqlalchemy>=2.0.0
Requires-Dist: cryptography>=43.0.0
